Metadata-Version: 2.1
Name: appall
Version: 0.1.0
Summary: Project for horizontally juxtapozing text in terminal
Home-page: https://github.com/zeionara/appall
Author: Zeio Nara
Author-email: zeionara@gmail.com
License: UNKNOWN
Platform: UNKNOWN
Classifier: Programming Language :: Python :: 3.10
License-File: LICENSE
